RoboZap.py
__init__.py
RoboZap-1.3.3.dist-info/METADATA
RoboZap-1.3.3.dist-info/WHEEL
RoboZap-1.3.3.dist-info/top_level.txt
RoboZap-1.3.3.dist-info/RECORD
