Metadata-Version: 2.1
Name: RoboZap
Version: 1.3.3
Summary: Robot Framework Library for the OWASP ZAP Application Vulnerability Scanner
Home-page: https://www.github.com/we45/RoboZap
Author: we45
Author-email: info@we45.com
License: MIT
Platform: UNKNOWN
Requires-Dist: requests (==2.25.1)
Requires-Dist: python-owasp-zap-v2.4 (==0.0.14)
Requires-Dist: robotframework (==3.0.4)
Requires-Dist: boto3 (==1.17.49)
